ntfyme/__init__.py
ntfyme/config.toml
ntfyme/main.py
ntfyme/notification.py
ntfyme/cmd/cmd_direct.py
ntfyme/cmd/cmd_pipe.py
ntfyme/cmd/live_capture.py
ntfyme/cmd/__pycache__/cmd_direct.cpython-312.pyc
ntfyme/cmd/__pycache__/cmd_pipe.cpython-312.pyc
ntfyme/cmd/__pycache__/live_capture.cpython-312.pyc
ntfyme/manager/encrypt.py
ntfyme/manager/setup_interaction.py
ntfyme/manager/__pycache__/encrypt.cpython-312.pyc
ntfyme/manager/__pycache__/setup_interaction.cpython-312.pyc
ntfyme/utils/local_notify/gen_notif.py
ntfyme/utils/local_notify/linux.py
ntfyme/utils/local_notify/macos.py
ntfyme/utils/local_notify/windows.py
ntfyme/utils/local_notify/__pycache__/gen_notif.cpython-312.pyc
ntfyme/utils/local_notify/__pycache__/linux.cpython-312.pyc
ntfyme/utils/local_notify/__pycache__/macos.cpython-312.pyc
ntfyme/utils/local_notify/__pycache__/windows.cpython-312.pyc
ntfyme/utils/log/log.py
ntfyme/utils/log/ntfyme.log
ntfyme/utils/log/__pycache__/log.cpython-312.pyc
ntfyme/utils/mail/gmail.py
ntfyme/utils/mail/telegram.py
ntfyme/utils/mail/__pycache__/gmail.cpython-312.pyc
ntfyme/utils/mail/__pycache__/telegram.cpython-312.pyc
ntfyme-0.0.1.dist-info/LICENSE
ntfyme-0.0.1.dist-info/METADATA
ntfyme-0.0.1.dist-info/WHEEL
ntfyme-0.0.1.dist-info/entry_points.txt
ntfyme-0.0.1.dist-info/top_level.txt
ntfyme-0.0.1.dist-info/RECORD
