Metadata-Version: 2.1
Name: ntfyme
Version: 0.0.1
Summary: Simple notification tool to notify yourself when a long running process ends with local ping, gmail, telegram, etc.
Home-page: https://github.com/AnirudhG07/ntfyme
Author: Anirudh Gupta
Keywords: notification,notify,cli,python
Classifier: Development Status :: 5 - Production/Stable
Classifier: Intended Audience :: Developers
Classifier: Programming Language :: Python :: 3.10
Classifier: Programming Language :: Python :: 3.11
Classifier: Programming Language :: Python :: 3.12
Classifier: License :: OSI Approved :: Apache Software License
Classifier: Topic :: Software Development
Classifier: Operating System :: POSIX
Classifier: Operating System :: MacOS
Classifier: Operating System :: Microsoft :: Windows
Requires-Python: >=3.10
License-File: LICENSE
Requires-Dist: toml
Requires-Dist: plyer
Requires-Dist: tomlkit
Requires-Dist: cryptography
Requires-Dist: requests
